  Compiled from "MethodReferenceTest.java"
public class invoke.MethodReferenceTest
  minor version: 0
  major version: 61
  flags: (0x0021) ACC_PUBLIC, ACC_SUPER
  this_class: #17                         // invoke/MethodReferenceTest
  super_class: #2                         // java/lang/Object
  interfaces: 0, fields: 0, methods: 3, attributes: 3
Constant pool:
   #1 = Methodref          #2.#3          // java/lang/Object."<init>":()V
   #2 = Class              #4             // java/lang/Object
   #3 = NameAndType        #5:#6          // "<init>":()V
   #4 = Utf8               java/lang/Object
   #5 = Utf8               <init>
   #6 = Utf8               ()V
   #7 = InterfaceMethodref #8.#9          // java/util/function/Supplier.get:()Ljava/lang/Object;
   #8 = Class              #10            // java/util/function/Supplier
   #9 = NameAndType        #11:#12        // get:()Ljava/lang/Object;
  #10 = Utf8               java/util/function/Supplier
  #11 = Utf8               get
  #12 = Utf8               ()Ljava/lang/Object;
  #13 = InvokeDynamic      #0:#14         // #0:get:()Ljava/util/function/Supplier;
  #14 = NameAndType        #11:#15        // get:()Ljava/util/function/Supplier;
  #15 = Utf8               ()Ljava/util/function/Supplier;
  #16 = Methodref          #17.#18        // invoke/MethodReferenceTest.consumer:(Ljava/util/function/Supplier;)V
  #17 = Class              #19            // invoke/MethodReferenceTest
  #18 = NameAndType        #20:#21        // consumer:(Ljava/util/function/Supplier;)V
  #19 = Utf8               invoke/MethodReferenceTest
  #20 = Utf8               consumer
  #21 = Utf8               (Ljava/util/function/Supplier;)V
  #22 = Utf8               Code
  #23 = Utf8               LineNumberTable
  #24 = Utf8               LocalVariableTable
  #25 = Utf8               this
  #26 = Utf8               Linvoke/MethodReferenceTest;
  #27 = Utf8               sup
  #28 = Utf8               Ljava/util/function/Supplier;
  #29 = Utf8               LocalVariableTypeTable
  #30 = Utf8               Ljava/util/function/Supplier<Ljava/lang/Object;>;
  #31 = Utf8               Signature
  #32 = Utf8               (Ljava/util/function/Supplier<Ljava/lang/Object;>;)V
  #33 = Utf8               testMethodReference
  #34 = Utf8               RuntimeVisibleAnnotations
  #35 = Utf8               Lorg/junit/jupiter/api/Test;
  #36 = Utf8               SourceFile

  #37 = Utf8               MethodReferenceTest.java
  #38 = Utf8               BootstrapMethods
  #39 = MethodHandle       6:#40          // REF_invokeStatic java/lang/invoke/LambdaMetafactory.metafactory:(Ljava/lang/invoke/MethodHandles$Lookup;Ljava/lang/String;Ljava/lang/invoke/MethodType;Ljava/lang/invoke/MethodType;Ljava/lang/invoke/MethodHandle;Ljava/lang/invoke/MethodType;)Ljava/lang/invoke/CallSite;
  #40 = Methodref          #41.#42        // java/lang/invoke/LambdaMetafactory.metafactory:(Ljava/lang/invoke/MethodHandles$Lookup;Ljava/lang/String;Ljava/lang/invoke/MethodType;Ljava/lang/invoke/MethodType;Ljava/lang/invoke/MethodHandle;Ljava/lang/invoke/MethodType;)Ljava/lang/invoke/CallSite;
  #41 = Class              #43            // java/lang/invoke/LambdaMetafactory
  #42 = NameAndType        #44:#45        // metafactory:(Ljava/lang/invoke/MethodHandles$Lookup;Ljava/lang/String;Ljava/lang/invoke/MethodType;Ljava/lang/invoke/MethodType;Ljava/lang/invoke/MethodHandle;Ljava/lang/invoke/MethodType;)Ljava/lang/invoke/CallSite;
  #43 = Utf8               java/lang/invoke/LambdaMetafactory
  #44 = Utf8               metafactory
  #45 = Utf8               (Ljava/lang/invoke/MethodHandles$Lookup;Ljava/lang/String;Ljava/lang/invoke/MethodType;Ljava/lang/invoke/MethodType;Ljava/lang/invoke/MethodHandle;Ljava/lang/invoke/MethodType;)Ljava/lang/invoke/CallSite;
  #46 = MethodType         #12            //  ()Ljava/lang/Object;
  #47 = MethodHandle       8:#1           // REF_newInvokeSpecial java/lang/Object."<init>":()V


  #48 = Utf8               InnerClasses
  #49 = Class              #50            // java/lang/invoke/MethodHandles$Lookup
  #50 = Utf8               java/lang/invoke/MethodHandles$Lookup
  #51 = Class              #52            // java/lang/invoke/MethodHandles
  #52 = Utf8               java/lang/invoke/MethodHandles
  #53 = Utf8               Lookup
{
  public invoke.MethodReferenceTest();
    descriptor: ()V
    flags: (0x0001) ACC_PUBLIC
    Code:
      stack=1, locals=1, args_size=1
         0: aload_0
         1: invokespecial #1                  // Method java/lang/Object."<init>":()V
         4: return
      LineNumberTable:
        line 7: 0
      LocalVariableTable:
        Start  Length  Slot  Name   Signature
            0       5     0  this   Linvoke/MethodReferenceTest;

  public static void consumer(java.util.function.Supplier<java.lang.Object>);
    descriptor: (Ljava/util/function/Supplier;)V
    flags: (0x0009) ACC_PUBLIC, ACC_STATIC
    Code:
      stack=1, locals=1, args_size=1
         0: aload_0
         1: invokeinterface #7,  1            // InterfaceMethod java/util/function/Supplier.get:()Ljava/lang/Object;
         6: pop
         7: return
      LineNumberTable:
        line 9: 0
        line 10: 7
      LocalVariableTable:
        Start  Length  Slot  Name   Signature
            0       8     0   sup   Ljava/util/function/Supplier;
      LocalVariableTypeTable:
        Start  Length  Slot  Name   Signature
            0       8     0   sup   Ljava/util/function/Supplier<Ljava/lang/Object;>;
    Signature: #32                          // (Ljava/util/function/Supplier<Ljava/lang/Object;>;)V

  void testMethodReference();
    descriptor: ()V
    flags: (0x0000)
    Code:
      stack=1, locals=1, args_size=1
         0: invokedynamic #13,  0             // InvokeDynamic #0:get:()Ljava/util/function/Supplier;
         5: invokestatic  #16                 // Method consumer:(Ljava/util/function/Supplier;)V
         8: return
      LineNumberTable:
        line 14: 0
        line 15: 8
      LocalVariableTable:
        Start  Length  Slot  Name   Signature
            0       9     0  this   Linvoke/MethodReferenceTest;
    RuntimeVisibleAnnotations:
      0: #35()
        org.junit.jupiter.api.Test
}
SourceFile: "MethodReferenceTest.java"
BootstrapMethods:
  0: #39 REF_invokeStatic java/lang/invoke/LambdaMetafactory.metafactory:(Ljava/lang/invoke/MethodHandles$Lookup;Ljava/lang/String;Ljava/lang/invoke/MethodType;Ljava/lang/invoke/MethodType;Ljava/lang/invoke/MethodHandle;Ljava/lang/invoke/MethodType;)Ljava/lang/invoke/CallSite;
    Method arguments:
      #46 ()Ljava/lang/Object;
      #47 REF_newInvokeSpecial java/lang/Object."<init>":()V
      #46 ()Ljava/lang/Object;
InnerClasses:
  public static final #53= #49 of #51;    // Lookup=class java/lang/invoke/MethodHandles$Lookup of class java/lang/invoke/MethodHandles